setup.py
django_gevent/__init__.py
django_gevent/fix_manage.sh
django_gevent.egg-info/PKG-INFO
django_gevent.egg-info/SOURCES.txt
django_gevent.egg-info/dependency_links.txt
django_gevent.egg-info/requires.txt
django_gevent.egg-info/top_level.txt
django_gevent/management/__init__.py
django_gevent/management/commands/__init__.py
django_gevent/management/commands/rungevent.py