Metadata-Version: 1.0
Name: django-gevent
Version: 0.1
Summary: Combine TCP server with Django based on gevent
Home-page: https://github.com/codemeow5/django-gevent
Author: CodeMeow5
Author-email: codemeow@yahoo.com
License: MIT
Keywords: django,gevent,tcp
Platform: UNKNOWN
